.DS_Store
github/passcode/__init__.py
passcode/__init__.py
passcode-0.1.6.dist-info/LICENSE
passcode-0.1.6.dist-info/METADATA
passcode-0.1.6.dist-info/WHEEL
passcode-0.1.6.dist-info/top_level.txt
passcode-0.1.6.dist-info/RECORD
