Metadata-Version: 2.1
Name: passcode
Version: 0.1.6
Summary: Encrypt modules to pass private code through a repository.
Home-page: https://github.com/KenYounge/passcode
Author: Ken Younge
Author-email: kenyounge@gmail.com
License: UNKNOWN
Platform: UNKNOWN
Classifier: Programming Language :: Python :: 3
Classifier: License :: OSI Approved :: MIT License
Classifier: Operating System :: OS Independent
Requires-Python: >=3.6
